<?xml version="1.0" encoding="UTF-8"?>
<orbits xmlns="urn:newtonpaths">
<result operation="Flyby">
<description>15/12/11 23:37 D:\perso\orbitfinder\ESbydv.2467065.xml:1 operation 6 after 76s.</description>
<orbit>
<parameter name="aproxMetricPar[0]" value="365.0"/>
<parameter name="aproxMetricPar[1]" value="1.0E-5"/>
<parameter name="aproxMetricPar[2]" value="3.141592653589793"/>
<parameter name="aproxMetricPar[3]" value="6.283185307179586"/>
<parameter name="aproxMetricPar[4]" value="1.0E-5"/>
<parameter name="aproxMetricPar[5]" value="6.283185307179586"/>
<parameter name="section.startBase[0][0]" value="-0.7677010853505211"/>
<parameter name="section.startBase[0][1]" value="0.5878903055324538"/>
<parameter name="section.startBase[0][2]" value="0.2549902590543216"/>
<parameter name="section.startBase[1][0]" value="-0.6408081100454643"/>
<parameter name="section.startBase[1][1]" value="-0.7043654731982253"/>
<parameter name="section.startBase[1][2]" value="-0.3053428339853421"/>
<parameter name="section.startBase[2][0]" value="9.824251594720002E-5"/>
<parameter name="section.startBase[2][1]" value="-0.3978118510391543"/>
<parameter name="section.startBase[2][2]" value="0.9174670138600132"/>
<parameter name="section.endBase[0][0]" value="-0.7677010853505211"/>
<parameter name="section.endBase[0][1]" value="0.5878903055324538"/>
<parameter name="section.endBase[0][2]" value="0.2549902590543216"/>
<parameter name="section.endBase[1][0]" value="-0.6408081100454643"/>
<parameter name="section.endBase[1][1]" value="-0.7043654731982253"/>
<parameter name="section.endBase[1][2]" value="-0.3053428339853421"/>
<parameter name="section.endBase[2][0]" value="9.824251594720002E-5"/>
<parameter name="section.endBase[2][1]" value="-0.3978118510391543"/>
<parameter name="section.endBase[2][2]" value="0.9174670138600132"/>
<parameter name="section.poincareStartVector[0]" value="0.07295970344051993"/>
<parameter name="section.poincareStartVector[1]" value="0.009999825904955004"/>
<parameter name="section.poincareStartVector[2]" value="1.5827012056410645"/>
<parameter name="section.poincareStartVector[3]" value="-0.6289460581612599"/>
<parameter name="section.poincareStartVector[4]" value="0.006251281235411684"/>
<parameter name="section.poincareStartVector[5]" value="-1.3426797349840023"/>
<parameter name="section.poincareMaxIterRef" value="20"/>
<parameter name="section.poincareMinTime" value="0.0"/>
<parameter name="section.poincareMaxTime" value="20000.0"/>
<parameter name="section.poincareStartBody" value="4"/>
<parameter name="section.poincareEndBody" value="7"/>
<parameter name="section.poincareSense" value="1"/>
<parameter name="section.epoch" value="2467260.331979402"/>
<parameter name="flyByCriterion" value="0.05"/>
<parameter name="aproxTolErr" value="1.0E-6"/>
<parameter name="aproxStepPar" value="5.0E-4"/>
<parameter name="aproxMinStepPar" value="1.0E-11"/>
<parameter name="aproxMaxIter" value="5000"/>
<parameter name="aproxEndBodyDistance" value="0.0050"/>
<parameter name="aproxInitialStartBodyDistance" value="0.01"/>
<parameter name="aproxInitialEndBodyDistance" value="8.0"/>
<parameter name="aproxInitialTime" value="2467065.0"/>
</orbit>
</result>
<result operation="Flyby">
<description>15/12/11 23:39 D:\perso\orbitfinder\ESbydv.2467065.xml:2 operation 6 after 83s.</description>
<orbit>
<parameter name="aproxMetricPar[0]" value="365.0"/>
<parameter name="aproxMetricPar[1]" value="1.0E-5"/>
<parameter name="aproxMetricPar[2]" value="3.141592653589793"/>
<parameter name="aproxMetricPar[3]" value="6.283185307179586"/>
<parameter name="aproxMetricPar[4]" value="1.0E-5"/>
<parameter name="aproxMetricPar[5]" value="6.283185307179586"/>
<parameter name="section.startBase[0][0]" value="-0.7677010853505211"/>
<parameter name="section.startBase[0][1]" value="0.5878903055324538"/>
<parameter name="section.startBase[0][2]" value="0.2549902590543216"/>
<parameter name="section.startBase[1][0]" value="-0.6408081100454643"/>
<parameter name="section.startBase[1][1]" value="-0.7043654731982253"/>
<parameter name="section.startBase[1][2]" value="-0.3053428339853421"/>
<parameter name="section.startBase[2][0]" value="9.824251594720002E-5"/>
<parameter name="section.startBase[2][1]" value="-0.3978118510391543"/>
<parameter name="section.startBase[2][2]" value="0.9174670138600132"/>
<parameter name="section.endBase[0][0]" value="-0.7677010853505211"/>
<parameter name="section.endBase[0][1]" value="0.5878903055324538"/>
<parameter name="section.endBase[0][2]" value="0.2549902590543216"/>
<parameter name="section.endBase[1][0]" value="-0.6408081100454643"/>
<parameter name="section.endBase[1][1]" value="-0.7043654731982253"/>
<parameter name="section.endBase[1][2]" value="-0.3053428339853421"/>
<parameter name="section.endBase[2][0]" value="9.824251594720002E-5"/>
<parameter name="section.endBase[2][1]" value="-0.3978118510391543"/>
<parameter name="section.endBase[2][2]" value="0.9174670138600132"/>
<parameter name="section.poincareStartVector[0]" value="0.08688562578661102"/>
<parameter name="section.poincareStartVector[1]" value="0.009999817048449076"/>
<parameter name="section.poincareStartVector[2]" value="1.5837473710819343"/>
<parameter name="section.poincareStartVector[3]" value="-0.6287322209952405"/>
<parameter name="section.poincareStartVector[4]" value="0.0062122574624616815"/>
<parameter name="section.poincareStartVector[5]" value="-1.3342490394060937"/>
<parameter name="section.poincareMaxIterRef" value="20"/>
<parameter name="section.poincareMinTime" value="0.0"/>
<parameter name="section.poincareMaxTime" value="20000.0"/>
<parameter name="section.poincareStartBody" value="4"/>
<parameter name="section.poincareEndBody" value="7"/>
<parameter name="section.poincareSense" value="1"/>
<parameter name="section.epoch" value="2467260.133352402"/>
<parameter name="flyByCriterion" value="0.05"/>
<parameter name="aproxTolErr" value="1.0E-6"/>
<parameter name="aproxStepPar" value="5.0E-4"/>
<parameter name="aproxMinStepPar" value="1.0E-11"/>
<parameter name="aproxMaxIter" value="5000"/>
<parameter name="aproxEndBodyDistance" value="0.0050"/>
<parameter name="aproxInitialStartBodyDistance" value="0.01"/>
<parameter name="aproxInitialEndBodyDistance" value="7.0"/>
<parameter name="aproxInitialTime" value="2467065.0"/>
</orbit>
</result>
<result operation="Flyby">
<description>15/12/11 23:40 D:\perso\orbitfinder\ESbydv.2467065.xml:3 operation 6 after 93s.</description>
<orbit>
<parameter name="aproxMetricPar[0]" value="365.0"/>
<parameter name="aproxMetricPar[1]" value="1.0E-5"/>
<parameter name="aproxMetricPar[2]" value="3.141592653589793"/>
<parameter name="aproxMetricPar[3]" value="6.283185307179586"/>
<parameter name="aproxMetricPar[4]" value="1.0E-5"/>
<parameter name="aproxMetricPar[5]" value="6.283185307179586"/>
<parameter name="section.startBase[0][0]" value="-0.7677010853505211"/>
<parameter name="section.startBase[0][1]" value="0.5878903055324538"/>
<parameter name="section.startBase[0][2]" value="0.2549902590543216"/>
<parameter name="section.startBase[1][0]" value="-0.6408081100454643"/>
<parameter name="section.startBase[1][1]" value="-0.7043654731982253"/>
<parameter name="section.startBase[1][2]" value="-0.3053428339853421"/>
<parameter name="section.startBase[2][0]" value="9.824251594720002E-5"/>
<parameter name="section.startBase[2][1]" value="-0.3978118510391543"/>
<parameter name="section.startBase[2][2]" value="0.9174670138600132"/>
<parameter name="section.endBase[0][0]" value="-0.7677010853505211"/>
<parameter name="section.endBase[0][1]" value="0.5878903055324538"/>
<parameter name="section.endBase[0][2]" value="0.2549902590543216"/>
<parameter name="section.endBase[1][0]" value="-0.6408081100454643"/>
<parameter name="section.endBase[1][1]" value="-0.7043654731982253"/>
<parameter name="section.endBase[1][2]" value="-0.3053428339853421"/>
<parameter name="section.endBase[2][0]" value="9.824251594720002E-5"/>
<parameter name="section.endBase[2][1]" value="-0.3978118510391543"/>
<parameter name="section.endBase[2][2]" value="0.9174670138600132"/>
<parameter name="section.poincareStartVector[0]" value="0.1111320981541208"/>
<parameter name="section.poincareStartVector[1]" value="0.009999838519873893"/>
<parameter name="section.poincareStartVector[2]" value="1.5852818912239799"/>
<parameter name="section.poincareStartVector[3]" value="-0.6257809290704333"/>
<parameter name="section.poincareStartVector[4]" value="0.006174538224151267"/>
<parameter name="section.poincareStartVector[5]" value="-1.3228819157467"/>
<parameter name="section.poincareMaxIterRef" value="20"/>
<parameter name="section.poincareMinTime" value="0.0"/>
<parameter name="section.poincareMaxTime" value="20000.0"/>
<parameter name="section.poincareStartBody" value="4"/>
<parameter name="section.poincareEndBody" value="7"/>
<parameter name="section.poincareSense" value="1"/>
<parameter name="section.epoch" value="2467259.9271742483"/>
<parameter name="flyByCriterion" value="0.05"/>
<parameter name="aproxTolErr" value="1.0E-6"/>
<parameter name="aproxStepPar" value="5.0E-4"/>
<parameter name="aproxMinStepPar" value="1.0E-11"/>
<parameter name="aproxMaxIter" value="5000"/>
<parameter name="aproxEndBodyDistance" value="0.0050"/>
<parameter name="aproxInitialStartBodyDistance" value="0.01"/>
<parameter name="aproxInitialEndBodyDistance" value="6.0"/>
<parameter name="aproxInitialTime" value="2467065.0"/>
</orbit>
</result>
<result operation="Flyby">
<description>15/12/11 23:42 D:\perso\orbitfinder\ESbydv.2467065.xml:4 operation 6 after 114s.</description>
<orbit>
<parameter name="aproxMetricPar[0]" value="365.0"/>
<parameter name="aproxMetricPar[1]" value="1.0E-5"/>
<parameter name="aproxMetricPar[2]" value="3.141592653589793"/>
<parameter name="aproxMetricPar[3]" value="6.283185307179586"/>
<parameter name="aproxMetricPar[4]" value="1.0E-5"/>
<parameter name="aproxMetricPar[5]" value="6.283185307179586"/>
<parameter name="section.startBase[0][0]" value="-0.7677010853505211"/>
<parameter name="section.startBase[0][1]" value="0.5878903055324538"/>
<parameter name="section.startBase[0][2]" value="0.2549902590543216"/>
<parameter name="section.startBase[1][0]" value="-0.6408081100454643"/>
<parameter name="section.startBase[1][1]" value="-0.7043654731982253"/>
<parameter name="section.startBase[1][2]" value="-0.3053428339853421"/>
<parameter name="section.startBase[2][0]" value="9.824251594720002E-5"/>
<parameter name="section.startBase[2][1]" value="-0.3978118510391543"/>
<parameter name="section.startBase[2][2]" value="0.9174670138600132"/>
<parameter name="section.endBase[0][0]" value="-0.7677010853505211"/>
<parameter name="section.endBase[0][1]" value="0.5878903055324538"/>
<parameter name="section.endBase[0][2]" value="0.2549902590543216"/>
<parameter name="section.endBase[1][0]" value="-0.6408081100454643"/>
<parameter name="section.endBase[1][1]" value="-0.7043654731982253"/>
<parameter name="section.endBase[1][2]" value="-0.3053428339853421"/>
<parameter name="section.endBase[2][0]" value="9.824251594720002E-5"/>
<parameter name="section.endBase[2][1]" value="-0.3978118510391543"/>
<parameter name="section.endBase[2][2]" value="0.9174670138600132"/>
<parameter name="section.poincareStartVector[0]" value="0.16420611781015348"/>
<parameter name="section.poincareStartVector[1]" value="0.010000028625750005"/>
<parameter name="section.poincareStartVector[2]" value="1.5883482284825423"/>
<parameter name="section.poincareStartVector[3]" value="-0.6178181760214557"/>
<parameter name="section.poincareStartVector[4]" value="0.006141598294378156"/>
<parameter name="section.poincareStartVector[5]" value="-1.3064575226538588"/>
<parameter name="section.poincareMaxIterRef" value="20"/>
<parameter name="section.poincareMinTime" value="0.0"/>
<parameter name="section.poincareMaxTime" value="20000.0"/>
<parameter name="section.poincareStartBody" value="4"/>
<parameter name="section.poincareEndBody" value="7"/>
<parameter name="section.poincareSense" value="1"/>
<parameter name="section.epoch" value="2467259.7225314532"/>
<parameter name="flyByCriterion" value="0.05"/>
<parameter name="aproxTolErr" value="1.0E-6"/>
<parameter name="aproxStepPar" value="5.0E-4"/>
<parameter name="aproxMinStepPar" value="1.0E-11"/>
<parameter name="aproxMaxIter" value="5000"/>
<parameter name="aproxEndBodyDistance" value="0.0050"/>
<parameter name="aproxInitialStartBodyDistance" value="0.01"/>
<parameter name="aproxInitialEndBodyDistance" value="5.0"/>
<parameter name="aproxInitialTime" value="2467065.0"/>
</orbit>
</result>
<result operation="Flyby">
<description>15/12/11 23:45 D:\perso\orbitfinder\ESbydv.2467065.xml:5 operation 6 after 159s.</description>
<orbit>
<parameter name="aproxMetricPar[0]" value="365.0"/>
<parameter name="aproxMetricPar[1]" value="1.0E-5"/>
<parameter name="aproxMetricPar[2]" value="3.141592653589793"/>
<parameter name="aproxMetricPar[3]" value="6.283185307179586"/>
<parameter name="aproxMetricPar[4]" value="1.0E-5"/>
<parameter name="aproxMetricPar[5]" value="6.283185307179586"/>
<parameter name="section.startBase[0][0]" value="-0.7677010853505211"/>
<parameter name="section.startBase[0][1]" value="0.5878903055324538"/>
<parameter name="section.startBase[0][2]" value="0.2549902590543216"/>
<parameter name="section.startBase[1][0]" value="-0.6408081100454643"/>
<parameter name="section.startBase[1][1]" value="-0.7043654731982253"/>
<parameter name="section.startBase[1][2]" value="-0.3053428339853421"/>
<parameter name="section.startBase[2][0]" value="9.824251594720002E-5"/>
<parameter name="section.startBase[2][1]" value="-0.3978118510391543"/>
<parameter name="section.startBase[2][2]" value="0.9174670138600132"/>
<parameter name="section.endBase[0][0]" value="-0.7677010853505211"/>
<parameter name="section.endBase[0][1]" value="0.5878903055324538"/>
<parameter name="section.endBase[0][2]" value="0.2549902590543216"/>
<parameter name="section.endBase[1][0]" value="-0.6408081100454643"/>
<parameter name="section.endBase[1][1]" value="-0.7043654731982253"/>
<parameter name="section.endBase[1][2]" value="-0.3053428339853421"/>
<parameter name="section.endBase[2][0]" value="9.824251594720002E-5"/>
<parameter name="section.endBase[2][1]" value="-0.3978118510391543"/>
<parameter name="section.endBase[2][2]" value="0.9174670138600132"/>
<parameter name="section.poincareStartVector[0]" value="0.2649784293133866"/>
<parameter name="section.poincareStartVector[1]" value="0.010000618254563935"/>
<parameter name="section.poincareStartVector[2]" value="1.5953569973669173"/>
<parameter name="section.poincareStartVector[3]" value="-0.6088625420034616"/>
<parameter name="section.poincareStartVector[4]" value="0.0061292979079078345"/>
<parameter name="section.poincareStartVector[5]" value="-1.2947607446405307"/>
<parameter name="section.poincareMaxIterRef" value="20"/>
<parameter name="section.poincareMinTime" value="0.0"/>
<parameter name="section.poincareMaxTime" value="20000.0"/>
<parameter name="section.poincareStartBody" value="4"/>
<parameter name="section.poincareEndBody" value="7"/>
<parameter name="section.poincareSense" value="1"/>
<parameter name="section.epoch" value="2467259.540902073"/>
<parameter name="flyByCriterion" value="0.05"/>
<parameter name="aproxTolErr" value="1.0E-6"/>
<parameter name="aproxStepPar" value="5.0E-4"/>
<parameter name="aproxMinStepPar" value="1.0E-11"/>
<parameter name="aproxMaxIter" value="5000"/>
<parameter name="aproxEndBodyDistance" value="0.0050"/>
<parameter name="aproxInitialStartBodyDistance" value="0.01"/>
<parameter name="aproxInitialEndBodyDistance" value="4.0"/>
<parameter name="aproxInitialTime" value="2467065.0"/>
</orbit>
</result>
<result operation="Flyby">
<description>15/12/11 23:47 D:\perso\orbitfinder\ESbydv.2467065.xml:6 operation 6 after 222s.</description>
<orbit>
<parameter name="aproxMetricPar[0]" value="365.0"/>
<parameter name="aproxMetricPar[1]" value="1.0E-5"/>
<parameter name="aproxMetricPar[2]" value="3.141592653589793"/>
<parameter name="aproxMetricPar[3]" value="6.283185307179586"/>
<parameter name="aproxMetricPar[4]" value="1.0E-5"/>
<parameter name="aproxMetricPar[5]" value="6.283185307179586"/>
<parameter name="section.startBase[0][0]" value="-0.7677010853505211"/>
<parameter name="section.startBase[0][1]" value="0.5878903055324538"/>
<parameter name="section.startBase[0][2]" value="0.2549902590543216"/>
<parameter name="section.startBase[1][0]" value="-0.6408081100454643"/>
<parameter name="section.startBase[1][1]" value="-0.7043654731982253"/>
<parameter name="section.startBase[1][2]" value="-0.3053428339853421"/>
<parameter name="section.startBase[2][0]" value="9.824251594720002E-5"/>
<parameter name="section.startBase[2][1]" value="-0.3978118510391543"/>
<parameter name="section.startBase[2][2]" value="0.9174670138600132"/>
<parameter name="section.endBase[0][0]" value="-0.7677010853505211"/>
<parameter name="section.endBase[0][1]" value="0.5878903055324538"/>
<parameter name="section.endBase[0][2]" value="0.2549902590543216"/>
<parameter name="section.endBase[1][0]" value="-0.6408081100454643"/>
<parameter name="section.endBase[1][1]" value="-0.7043654731982253"/>
<parameter name="section.endBase[1][2]" value="-0.3053428339853421"/>
<parameter name="section.endBase[2][0]" value="9.824251594720002E-5"/>
<parameter name="section.endBase[2][1]" value="-0.3978118510391543"/>
<parameter name="section.endBase[2][2]" value="0.9174670138600132"/>
<parameter name="section.poincareStartVector[0]" value="0.41616485552907695"/>
<parameter name="section.poincareStartVector[1]" value="0.010001480168683765"/>
<parameter name="section.poincareStartVector[2]" value="1.6096479907402492"/>
<parameter name="section.poincareStartVector[3]" value="-0.60266838691165"/>
<parameter name="section.poincareStartVector[4]" value="0.006121700901691988"/>
<parameter name="section.poincareStartVector[5]" value="-1.2931439382101328"/>
<parameter name="section.poincareMaxIterRef" value="20"/>
<parameter name="section.poincareMinTime" value="0.0"/>
<parameter name="section.poincareMaxTime" value="20000.0"/>
<parameter name="section.poincareStartBody" value="4"/>
<parameter name="section.poincareEndBody" value="7"/>
<parameter name="section.poincareSense" value="1"/>
<parameter name="section.epoch" value="2467259.4350544126"/>
<parameter name="flyByCriterion" value="0.05"/>
<parameter name="aproxTolErr" value="1.0E-6"/>
<parameter name="aproxStepPar" value="5.0E-4"/>
<parameter name="aproxMinStepPar" value="1.0E-11"/>
<parameter name="aproxMaxIter" value="5000"/>
<parameter name="aproxEndBodyDistance" value="0.0050"/>
<parameter name="aproxInitialStartBodyDistance" value="0.01"/>
<parameter name="aproxInitialEndBodyDistance" value="3.0"/>
<parameter name="aproxInitialTime" value="2467065.0"/>
</orbit>
</result>
<result operation="Flyby">
<description>15/12/11 23:52 D:\perso\orbitfinder\ESbydv.2467065.xml:8 operation 6 after 274s.</description>
<orbit>
<parameter name="aproxMetricPar[0]" value="365.0"/>
<parameter name="aproxMetricPar[1]" value="1.0E-5"/>
<parameter name="aproxMetricPar[2]" value="3.141592653589793"/>
<parameter name="aproxMetricPar[3]" value="6.283185307179586"/>
<parameter name="aproxMetricPar[4]" value="1.0E-5"/>
<parameter name="aproxMetricPar[5]" value="6.283185307179586"/>
<parameter name="section.startBase[0][0]" value="-0.7677010853505211"/>
<parameter name="section.startBase[0][1]" value="0.5878903055324538"/>
<parameter name="section.startBase[0][2]" value="0.2549902590543216"/>
<parameter name="section.startBase[1][0]" value="-0.6408081100454643"/>
<parameter name="section.startBase[1][1]" value="-0.7043654731982253"/>
<parameter name="section.startBase[1][2]" value="-0.3053428339853421"/>
<parameter name="section.startBase[2][0]" value="9.824251594720002E-5"/>
<parameter name="section.startBase[2][1]" value="-0.3978118510391543"/>
<parameter name="section.startBase[2][2]" value="0.9174670138600132"/>
<parameter name="section.endBase[0][0]" value="-0.7677010853505211"/>
<parameter name="section.endBase[0][1]" value="0.5878903055324538"/>
<parameter name="section.endBase[0][2]" value="0.2549902590543216"/>
<parameter name="section.endBase[1][0]" value="-0.6408081100454643"/>
<parameter name="section.endBase[1][1]" value="-0.7043654731982253"/>
<parameter name="section.endBase[1][2]" value="-0.3053428339853421"/>
<parameter name="section.endBase[2][0]" value="9.824251594720002E-5"/>
<parameter name="section.endBase[2][1]" value="-0.3978118510391543"/>
<parameter name="section.endBase[2][2]" value="0.9174670138600132"/>
<parameter name="section.poincareStartVector[0]" value="0.3163241931107486"/>
<parameter name="section.poincareStartVector[1]" value="0.010000769418737794"/>
<parameter name="section.poincareStartVector[2]" value="1.5971460876277408"/>
<parameter name="section.poincareStartVector[3]" value="-0.38467143218811645"/>
<parameter name="section.poincareStartVector[4]" value="0.0059437398691978985"/>
<parameter name="section.poincareStartVector[5]" value="-1.5840943481322558"/>
<parameter name="section.poincareMaxIterRef" value="20"/>
<parameter name="section.poincareMinTime" value="0.0"/>
<parameter name="section.poincareMaxTime" value="20000.0"/>
<parameter name="section.poincareStartBody" value="4"/>
<parameter name="section.poincareEndBody" value="7"/>
<parameter name="section.poincareSense" value="1"/>
<parameter name="section.epoch" value="2467260.4474309073"/>
<parameter name="flyByCriterion" value="0.05"/>
<parameter name="aproxTolErr" value="1.0E-6"/>
<parameter name="aproxStepPar" value="5.0E-4"/>
<parameter name="aproxMinStepPar" value="1.0E-11"/>
<parameter name="aproxMaxIter" value="5000"/>
<parameter name="aproxEndBodyDistance" value="0.0050"/>
<parameter name="aproxInitialStartBodyDistance" value="0.01"/>
<parameter name="aproxInitialEndBodyDistance" value="1.0"/>
<parameter name="aproxInitialTime" value="2467065.0"/>
</orbit>
</result>
<result operation="Flyby">
<description>15/12/11 23:52 D:\perso\orbitfinder\ESbydv.2467065.xml:7 operation 6 after 401s.</description>
<orbit>
<parameter name="aproxMetricPar[0]" value="365.0"/>
<parameter name="aproxMetricPar[1]" value="1.0E-5"/>
<parameter name="aproxMetricPar[2]" value="3.141592653589793"/>
<parameter name="aproxMetricPar[3]" value="6.283185307179586"/>
<parameter name="aproxMetricPar[4]" value="1.0E-5"/>
<parameter name="aproxMetricPar[5]" value="6.283185307179586"/>
<parameter name="section.startBase[0][0]" value="-0.7677010853505211"/>
<parameter name="section.startBase[0][1]" value="0.5878903055324538"/>
<parameter name="section.startBase[0][2]" value="0.2549902590543216"/>
<parameter name="section.startBase[1][0]" value="-0.6408081100454643"/>
<parameter name="section.startBase[1][1]" value="-0.7043654731982253"/>
<parameter name="section.startBase[1][2]" value="-0.3053428339853421"/>
<parameter name="section.startBase[2][0]" value="9.824251594720002E-5"/>
<parameter name="section.startBase[2][1]" value="-0.3978118510391543"/>
<parameter name="section.startBase[2][2]" value="0.9174670138600132"/>
<parameter name="section.endBase[0][0]" value="-0.7677010853505211"/>
<parameter name="section.endBase[0][1]" value="0.5878903055324538"/>
<parameter name="section.endBase[0][2]" value="0.2549902590543216"/>
<parameter name="section.endBase[1][0]" value="-0.6408081100454643"/>
<parameter name="section.endBase[1][1]" value="-0.7043654731982253"/>
<parameter name="section.endBase[1][2]" value="-0.3053428339853421"/>
<parameter name="section.endBase[2][0]" value="9.824251594720002E-5"/>
<parameter name="section.endBase[2][1]" value="-0.3978118510391543"/>
<parameter name="section.endBase[2][2]" value="0.9174670138600132"/>
<parameter name="section.poincareStartVector[0]" value="0.49282961495722166"/>
<parameter name="section.poincareStartVector[1]" value="0.01000022020354793"/>
<parameter name="section.poincareStartVector[2]" value="1.6128100653348636"/>
<parameter name="section.poincareStartVector[3]" value="-0.3696442358685257"/>
<parameter name="section.poincareStartVector[4]" value="0.005976226628339296"/>
<parameter name="section.poincareStartVector[5]" value="-1.5704310036302385"/>
<parameter name="section.poincareMaxIterRef" value="20"/>
<parameter name="section.poincareMinTime" value="0.0"/>
<parameter name="section.poincareMaxTime" value="20000.0"/>
<parameter name="section.poincareStartBody" value="4"/>
<parameter name="section.poincareEndBody" value="7"/>
<parameter name="section.poincareSense" value="1"/>
<parameter name="section.epoch" value="2467259.5519469585"/>
<parameter name="flyByCriterion" value="0.05"/>
<parameter name="aproxTolErr" value="1.0E-6"/>
<parameter name="aproxStepPar" value="5.0E-4"/>
<parameter name="aproxMinStepPar" value="1.0E-11"/>
<parameter name="aproxMaxIter" value="5000"/>
<parameter name="aproxEndBodyDistance" value="0.0050"/>
<parameter name="aproxInitialStartBodyDistance" value="0.01"/>
<parameter name="aproxInitialEndBodyDistance" value="2.0"/>
<parameter name="aproxInitialTime" value="2467065.0"/>
</orbit>
</result>
<result operation="Flyby">
<description>15/12/11 23:56 D:\perso\orbitfinder\ESbydv.2467065.xml:9 operation 6 after 230s.</description>
<orbit>
<parameter name="aproxMetricPar[0]" value="365.0"/>
<parameter name="aproxMetricPar[1]" value="1.0E-5"/>
<parameter name="aproxMetricPar[2]" value="3.141592653589793"/>
<parameter name="aproxMetricPar[3]" value="6.283185307179586"/>
<parameter name="aproxMetricPar[4]" value="1.0E-5"/>
<parameter name="aproxMetricPar[5]" value="6.283185307179586"/>
<parameter name="section.startBase[0][0]" value="-0.7677010853505211"/>
<parameter name="section.startBase[0][1]" value="0.5878903055324538"/>
<parameter name="section.startBase[0][2]" value="0.2549902590543216"/>
<parameter name="section.startBase[1][0]" value="-0.6408081100454643"/>
<parameter name="section.startBase[1][1]" value="-0.7043654731982253"/>
<parameter name="section.startBase[1][2]" value="-0.3053428339853421"/>
<parameter name="section.startBase[2][0]" value="9.824251594720002E-5"/>
<parameter name="section.startBase[2][1]" value="-0.3978118510391543"/>
<parameter name="section.startBase[2][2]" value="0.9174670138600132"/>
<parameter name="section.endBase[0][0]" value="-0.7677010853505211"/>
<parameter name="section.endBase[0][1]" value="0.5878903055324538"/>
<parameter name="section.endBase[0][2]" value="0.2549902590543216"/>
<parameter name="section.endBase[1][0]" value="-0.6408081100454643"/>
<parameter name="section.endBase[1][1]" value="-0.7043654731982253"/>
<parameter name="section.endBase[1][2]" value="-0.3053428339853421"/>
<parameter name="section.endBase[2][0]" value="9.824251594720002E-5"/>
<parameter name="section.endBase[2][1]" value="-0.3978118510391543"/>
<parameter name="section.endBase[2][2]" value="0.9174670138600132"/>
<parameter name="section.poincareStartVector[0]" value="0.23692817925531115"/>
<parameter name="section.poincareStartVector[1]" value="0.010000909993590571"/>
<parameter name="section.poincareStartVector[2]" value="1.5927184049037963"/>
<parameter name="section.poincareStartVector[3]" value="-0.39880230615008094"/>
<parameter name="section.poincareStartVector[4]" value="0.005900477395311857"/>
<parameter name="section.poincareStartVector[5]" value="-1.5783828467715664"/>
<parameter name="section.poincareMaxIterRef" value="20"/>
<parameter name="section.poincareMinTime" value="0.0"/>
<parameter name="section.poincareMaxTime" value="20000.0"/>
<parameter name="section.poincareStartBody" value="4"/>
<parameter name="section.poincareEndBody" value="7"/>
<parameter name="section.poincareSense" value="1"/>
<parameter name="section.epoch" value="2467262.07284011"/>
<parameter name="flyByCriterion" value="0.05"/>
<parameter name="aproxTolErr" value="1.0E-6"/>
<parameter name="aproxStepPar" value="5.0E-4"/>
<parameter name="aproxMinStepPar" value="1.0E-11"/>
<parameter name="aproxMaxIter" value="5000"/>
<parameter name="aproxEndBodyDistance" value="0.0050"/>
<parameter name="aproxInitialStartBodyDistance" value="0.01"/>
<parameter name="aproxInitialEndBodyDistance" value="0.5"/>
<parameter name="aproxInitialTime" value="2467065.0"/>
</orbit>
</result>
</orbits>
