<?xml version="1.0" encoding="UTF-8"?>
<orbits xmlns="urn:newtonpaths">
	<result operation="Flyby">
		<description>15/11/11 20:21 D:\perso\orbitfinder\24-ESbydv-2021.xml:1
			operation 2 after 116s.</description>
		<orbit>
			<parameter name="aproxMetricPar[0]" value="365.0" />
			<parameter name="aproxMetricPar[1]" value="1.0E-5" />
			<parameter name="aproxMetricPar[2]" value="3.141592653589793" />
			<parameter name="aproxMetricPar[3]" value="6.283185307179586" />
			<parameter name="aproxMetricPar[4]" value="1.0E-5" />
			<parameter name="aproxMetricPar[5]" value="6.283185307179586" />
			<parameter name="section.startBase[0][0]" value="-0.7677010853505211" />
			<parameter name="section.startBase[0][1]" value="0.5878903055324538" />
			<parameter name="section.startBase[0][2]" value="0.2549902590543216" />
			<parameter name="section.startBase[1][0]" value="-0.6408081100454643" />
			<parameter name="section.startBase[1][1]" value="-0.7043654731982253" />
			<parameter name="section.startBase[1][2]" value="-0.3053428339853421" />
			<parameter name="section.startBase[2][0]" value="9.824251594720002E-5" />
			<parameter name="section.startBase[2][1]" value="-0.3978118510391543" />
			<parameter name="section.startBase[2][2]" value="0.9174670138600132" />
			<parameter name="section.endBase[0][0]" value="-0.7677010853505211" />
			<parameter name="section.endBase[0][1]" value="0.5878903055324538" />
			<parameter name="section.endBase[0][2]" value="0.2549902590543216" />
			<parameter name="section.endBase[1][0]" value="-0.6408081100454643" />
			<parameter name="section.endBase[1][1]" value="-0.7043654731982253" />
			<parameter name="section.endBase[1][2]" value="-0.3053428339853421" />
			<parameter name="section.endBase[2][0]" value="9.824251594720002E-5" />
			<parameter name="section.endBase[2][1]" value="-0.3978118510391543" />
			<parameter name="section.endBase[2][2]" value="0.9174670138600132" />
			<parameter name="section.poincareStartVector[0]" value="0.08348817617525604" />
			<parameter name="section.poincareStartVector[1]" value="0.010002415018894704" />
			<parameter name="section.poincareStartVector[2]" value="1.5524280768601992" />
			<parameter name="section.poincareStartVector[3]" value="1.0586731514037715" />
			<parameter name="section.poincareStartVector[4]" value="0.006456771762642727" />
			<parameter name="section.poincareStartVector[5]" value="-1.90412016312049" />
			<parameter name="section.poincareMaxIterRef" value="20" />
			<parameter name="section.poincareMinTime" value="0.0" />
			<parameter name="section.poincareMaxTime" value="20000.0" />
			<parameter name="section.poincareStartBody" value="4" />
			<parameter name="section.poincareEndBody" value="7" />
			<parameter name="section.poincareSense" value="1" />
			<parameter name="section.epoch" value="2459686.0445730835" />
			<parameter name="flyByCriterion" value="0.05" />
			<parameter name="aproxTolErr" value="1.0E-6" />
			<parameter name="aproxStepPar" value="5.0E-4" />
			<parameter name="aproxMinStepPar" value="1.0E-11" />
			<parameter name="aproxMaxIter" value="5000" />
			<parameter name="aproxEndBodyDistance" value="0.0050" />
			<parameter name="aproxInitialStartBodyDistance" value="0.01" />
			<parameter name="aproxInitialEndBodyDistance" value="6.0" />
			<parameter name="aproxInitialTime" value="2459503.0" />
		</orbit>
	</result>
	<result operation="Flyby">
		<description>15/11/11 20:24 D:\perso\orbitfinder\24-ESbydv-2021.xml:2
			operation 2 after 128s.</description>
		<orbit>
			<parameter name="aproxMetricPar[0]" value="365.0" />
			<parameter name="aproxMetricPar[1]" value="1.0E-5" />
			<parameter name="aproxMetricPar[2]" value="3.141592653589793" />
			<parameter name="aproxMetricPar[3]" value="6.283185307179586" />
			<parameter name="aproxMetricPar[4]" value="1.0E-5" />
			<parameter name="aproxMetricPar[5]" value="6.283185307179586" />
			<parameter name="section.startBase[0][0]" value="-0.7677010853505211" />
			<parameter name="section.startBase[0][1]" value="0.5878903055324538" />
			<parameter name="section.startBase[0][2]" value="0.2549902590543216" />
			<parameter name="section.startBase[1][0]" value="-0.6408081100454643" />
			<parameter name="section.startBase[1][1]" value="-0.7043654731982253" />
			<parameter name="section.startBase[1][2]" value="-0.3053428339853421" />
			<parameter name="section.startBase[2][0]" value="9.824251594720002E-5" />
			<parameter name="section.startBase[2][1]" value="-0.3978118510391543" />
			<parameter name="section.startBase[2][2]" value="0.9174670138600132" />
			<parameter name="section.endBase[0][0]" value="-0.7677010853505211" />
			<parameter name="section.endBase[0][1]" value="0.5878903055324538" />
			<parameter name="section.endBase[0][2]" value="0.2549902590543216" />
			<parameter name="section.endBase[1][0]" value="-0.6408081100454643" />
			<parameter name="section.endBase[1][1]" value="-0.7043654731982253" />
			<parameter name="section.endBase[1][2]" value="-0.3053428339853421" />
			<parameter name="section.endBase[2][0]" value="9.824251594720002E-5" />
			<parameter name="section.endBase[2][1]" value="-0.3978118510391543" />
			<parameter name="section.endBase[2][2]" value="0.9174670138600132" />
			<parameter name="section.poincareStartVector[0]" value="0.10264606742163938" />
			<parameter name="section.poincareStartVector[1]" value="0.010002969239716775" />
			<parameter name="section.poincareStartVector[2]" value="1.550628286762451" />
			<parameter name="section.poincareStartVector[3]" value="1.0579283611331602" />
			<parameter name="section.poincareStartVector[4]" value="0.006450844056223317" />
			<parameter name="section.poincareStartVector[5]" value="-1.9115223164579296" />
			<parameter name="section.poincareMaxIterRef" value="20" />
			<parameter name="section.poincareMinTime" value="0.0" />
			<parameter name="section.poincareMaxTime" value="20000.0" />
			<parameter name="section.poincareStartBody" value="4" />
			<parameter name="section.poincareEndBody" value="7" />
			<parameter name="section.poincareSense" value="1" />
			<parameter name="section.epoch" value="2459685.9888542923" />
			<parameter name="flyByCriterion" value="0.05" />
			<parameter name="aproxTolErr" value="1.0E-6" />
			<parameter name="aproxStepPar" value="5.0E-4" />
			<parameter name="aproxMinStepPar" value="1.0E-11" />
			<parameter name="aproxMaxIter" value="5000" />
			<parameter name="aproxEndBodyDistance" value="0.0050" />
			<parameter name="aproxInitialStartBodyDistance" value="0.01" />
			<parameter name="aproxInitialEndBodyDistance" value="5.0" />
			<parameter name="aproxInitialTime" value="2459503.0" />
		</orbit>
	</result>
	<result operation="Flyby">
		<description>15/11/11 20:24 D:\perso\orbitfinder\24-ESbydv-2021.xml:3
			operation 2 after 139s.</description>
		<orbit>
			<parameter name="aproxMetricPar[0]" value="365.0" />
			<parameter name="aproxMetricPar[1]" value="1.0E-5" />
			<parameter name="aproxMetricPar[2]" value="3.141592653589793" />
			<parameter name="aproxMetricPar[3]" value="6.283185307179586" />
			<parameter name="aproxMetricPar[4]" value="1.0E-5" />
			<parameter name="aproxMetricPar[5]" value="6.283185307179586" />
			<parameter name="section.startBase[0][0]" value="-0.7677010853505211" />
			<parameter name="section.startBase[0][1]" value="0.5878903055324538" />
			<parameter name="section.startBase[0][2]" value="0.2549902590543216" />
			<parameter name="section.startBase[1][0]" value="-0.6408081100454643" />
			<parameter name="section.startBase[1][1]" value="-0.7043654731982253" />
			<parameter name="section.startBase[1][2]" value="-0.3053428339853421" />
			<parameter name="section.startBase[2][0]" value="9.824251594720002E-5" />
			<parameter name="section.startBase[2][1]" value="-0.3978118510391543" />
			<parameter name="section.startBase[2][2]" value="0.9174670138600132" />
			<parameter name="section.endBase[0][0]" value="-0.7677010853505211" />
			<parameter name="section.endBase[0][1]" value="0.5878903055324538" />
			<parameter name="section.endBase[0][2]" value="0.2549902590543216" />
			<parameter name="section.endBase[1][0]" value="-0.6408081100454643" />
			<parameter name="section.endBase[1][1]" value="-0.7043654731982253" />
			<parameter name="section.endBase[1][2]" value="-0.3053428339853421" />
			<parameter name="section.endBase[2][0]" value="9.824251594720002E-5" />
			<parameter name="section.endBase[2][1]" value="-0.3978118510391543" />
			<parameter name="section.endBase[2][2]" value="0.9174670138600132" />
			<parameter name="section.poincareStartVector[0]" value="0.11818496697224307" />
			<parameter name="section.poincareStartVector[1]" value="0.01000363916911093" />
			<parameter name="section.poincareStartVector[2]" value="1.548525336713717" />
			<parameter name="section.poincareStartVector[3]" value="1.057072434676583" />
			<parameter name="section.poincareStartVector[4]" value="0.006446757676456758" />
			<parameter name="section.poincareStartVector[5]" value="-1.9158266574287612" />
			<parameter name="section.poincareMaxIterRef" value="20" />
			<parameter name="section.poincareMinTime" value="0.0" />
			<parameter name="section.poincareMaxTime" value="20000.0" />
			<parameter name="section.poincareStartBody" value="4" />
			<parameter name="section.poincareEndBody" value="7" />
			<parameter name="section.poincareSense" value="1" />
			<parameter name="section.epoch" value="2459686.007940761" />
			<parameter name="flyByCriterion" value="0.05" />
			<parameter name="aproxTolErr" value="1.0E-6" />
			<parameter name="aproxStepPar" value="5.0E-4" />
			<parameter name="aproxMinStepPar" value="1.0E-11" />
			<parameter name="aproxMaxIter" value="5000" />
			<parameter name="aproxEndBodyDistance" value="0.0050" />
			<parameter name="aproxInitialStartBodyDistance" value="0.01" />
			<parameter name="aproxInitialEndBodyDistance" value="4.0" />
			<parameter name="aproxInitialTime" value="2459503.0" />
		</orbit>
	</result>
	<result operation="Flyby">
		<description>15/11/11 20:26 D:\perso\orbitfinder\24-ESbydv-2021.xml:4
			operation 2 after 149s.</description>
		<orbit>
			<parameter name="aproxMetricPar[0]" value="365.0" />
			<parameter name="aproxMetricPar[1]" value="1.0E-5" />
			<parameter name="aproxMetricPar[2]" value="3.141592653589793" />
			<parameter name="aproxMetricPar[3]" value="6.283185307179586" />
			<parameter name="aproxMetricPar[4]" value="1.0E-5" />
			<parameter name="aproxMetricPar[5]" value="6.283185307179586" />
			<parameter name="section.startBase[0][0]" value="-0.7677010853505211" />
			<parameter name="section.startBase[0][1]" value="0.5878903055324538" />
			<parameter name="section.startBase[0][2]" value="0.2549902590543216" />
			<parameter name="section.startBase[1][0]" value="-0.6408081100454643" />
			<parameter name="section.startBase[1][1]" value="-0.7043654731982253" />
			<parameter name="section.startBase[1][2]" value="-0.3053428339853421" />
			<parameter name="section.startBase[2][0]" value="9.824251594720002E-5" />
			<parameter name="section.startBase[2][1]" value="-0.3978118510391543" />
			<parameter name="section.startBase[2][2]" value="0.9174670138600132" />
			<parameter name="section.endBase[0][0]" value="-0.7677010853505211" />
			<parameter name="section.endBase[0][1]" value="0.5878903055324538" />
			<parameter name="section.endBase[0][2]" value="0.2549902590543216" />
			<parameter name="section.endBase[1][0]" value="-0.6408081100454643" />
			<parameter name="section.endBase[1][1]" value="-0.7043654731982253" />
			<parameter name="section.endBase[1][2]" value="-0.3053428339853421" />
			<parameter name="section.endBase[2][0]" value="9.824251594720002E-5" />
			<parameter name="section.endBase[2][1]" value="-0.3978118510391543" />
			<parameter name="section.endBase[2][2]" value="0.9174670138600132" />
			<parameter name="section.poincareStartVector[0]" value="0.1200151921595738" />
			<parameter name="section.poincareStartVector[1]" value="0.010004415269063108" />
			<parameter name="section.poincareStartVector[2]" value="1.5458932025041778" />
			<parameter name="section.poincareStartVector[3]" value="1.0546737438355227" />
			<parameter name="section.poincareStartVector[4]" value="0.00644195369626459" />
			<parameter name="section.poincareStartVector[5]" value="-1.917155917706601" />
			<parameter name="section.poincareMaxIterRef" value="20" />
			<parameter name="section.poincareMinTime" value="0.0" />
			<parameter name="section.poincareMaxTime" value="20000.0" />
			<parameter name="section.poincareStartBody" value="4" />
			<parameter name="section.poincareEndBody" value="7" />
			<parameter name="section.poincareSense" value="1" />
			<parameter name="section.epoch" value="2459686.1902687172" />
			<parameter name="flyByCriterion" value="0.05" />
			<parameter name="aproxTolErr" value="1.0E-6" />
			<parameter name="aproxStepPar" value="5.0E-4" />
			<parameter name="aproxMinStepPar" value="1.0E-11" />
			<parameter name="aproxMaxIter" value="5000" />
			<parameter name="aproxEndBodyDistance" value="0.0050" />
			<parameter name="aproxInitialStartBodyDistance" value="0.01" />
			<parameter name="aproxInitialEndBodyDistance" value="3.0" />
			<parameter name="aproxInitialTime" value="2459503.0" />
		</orbit>
	</result>
	<result operation="Flyby">
		<description>15/11/11 20:27 D:\perso\orbitfinder\24-ESbydv-2021.xml:5
			operation 2 after 159s.</description>
		<orbit>
			<parameter name="aproxMetricPar[0]" value="365.0" />
			<parameter name="aproxMetricPar[1]" value="1.0E-5" />
			<parameter name="aproxMetricPar[2]" value="3.141592653589793" />
			<parameter name="aproxMetricPar[3]" value="6.283185307179586" />
			<parameter name="aproxMetricPar[4]" value="1.0E-5" />
			<parameter name="aproxMetricPar[5]" value="6.283185307179586" />
			<parameter name="section.startBase[0][0]" value="-0.7677010853505211" />
			<parameter name="section.startBase[0][1]" value="0.5878903055324538" />
			<parameter name="section.startBase[0][2]" value="0.2549902590543216" />
			<parameter name="section.startBase[1][0]" value="-0.6408081100454643" />
			<parameter name="section.startBase[1][1]" value="-0.7043654731982253" />
			<parameter name="section.startBase[1][2]" value="-0.3053428339853421" />
			<parameter name="section.startBase[2][0]" value="9.824251594720002E-5" />
			<parameter name="section.startBase[2][1]" value="-0.3978118510391543" />
			<parameter name="section.startBase[2][2]" value="0.9174670138600132" />
			<parameter name="section.endBase[0][0]" value="-0.7677010853505211" />
			<parameter name="section.endBase[0][1]" value="0.5878903055324538" />
			<parameter name="section.endBase[0][2]" value="0.2549902590543216" />
			<parameter name="section.endBase[1][0]" value="-0.6408081100454643" />
			<parameter name="section.endBase[1][1]" value="-0.7043654731982253" />
			<parameter name="section.endBase[1][2]" value="-0.3053428339853421" />
			<parameter name="section.endBase[2][0]" value="9.824251594720002E-5" />
			<parameter name="section.endBase[2][1]" value="-0.3978118510391543" />
			<parameter name="section.endBase[2][2]" value="0.9174670138600132" />
			<parameter name="section.poincareStartVector[0]" value="0.08387161287641436" />
			<parameter name="section.poincareStartVector[1]" value="0.010005273143303238" />
			<parameter name="section.poincareStartVector[2]" value="1.5419119995789894" />
			<parameter name="section.poincareStartVector[3]" value="1.047591583935531" />
			<parameter name="section.poincareStartVector[4]" value="0.006433321441166299" />
			<parameter name="section.poincareStartVector[5]" value="-1.9149799240930117" />
			<parameter name="section.poincareMaxIterRef" value="20" />
			<parameter name="section.poincareMinTime" value="0.0" />
			<parameter name="section.poincareMaxTime" value="20000.0" />
			<parameter name="section.poincareStartBody" value="4" />
			<parameter name="section.poincareEndBody" value="7" />
			<parameter name="section.poincareSense" value="1" />
			<parameter name="section.epoch" value="2459686.7669271864" />
			<parameter name="flyByCriterion" value="0.05" />
			<parameter name="aproxTolErr" value="1.0E-6" />
			<parameter name="aproxStepPar" value="5.0E-4" />
			<parameter name="aproxMinStepPar" value="1.0E-11" />
			<parameter name="aproxMaxIter" value="5000" />
			<parameter name="aproxEndBodyDistance" value="0.0050" />
			<parameter name="aproxInitialStartBodyDistance" value="0.01" />
			<parameter name="aproxInitialEndBodyDistance" value="2.0" />
			<parameter name="aproxInitialTime" value="2459503.0" />
		</orbit>
	</result>
	<result operation="Flyby">
		<description>15/11/11 20:29 D:\perso\orbitfinder\24-ESbydv-2021.xml:6
			operation 2 after 156s.</description>
		<orbit>
			<parameter name="aproxMetricPar[0]" value="365.0" />
			<parameter name="aproxMetricPar[1]" value="1.0E-5" />
			<parameter name="aproxMetricPar[2]" value="3.141592653589793" />
			<parameter name="aproxMetricPar[3]" value="6.283185307179586" />
			<parameter name="aproxMetricPar[4]" value="1.0E-5" />
			<parameter name="aproxMetricPar[5]" value="6.283185307179586" />
			<parameter name="section.startBase[0][0]" value="-0.7677010853505211" />
			<parameter name="section.startBase[0][1]" value="0.5878903055324538" />
			<parameter name="section.startBase[0][2]" value="0.2549902590543216" />
			<parameter name="section.startBase[1][0]" value="-0.6408081100454643" />
			<parameter name="section.startBase[1][1]" value="-0.7043654731982253" />
			<parameter name="section.startBase[1][2]" value="-0.3053428339853421" />
			<parameter name="section.startBase[2][0]" value="9.824251594720002E-5" />
			<parameter name="section.startBase[2][1]" value="-0.3978118510391543" />
			<parameter name="section.startBase[2][2]" value="0.9174670138600132" />
			<parameter name="section.endBase[0][0]" value="-0.7677010853505211" />
			<parameter name="section.endBase[0][1]" value="0.5878903055324538" />
			<parameter name="section.endBase[0][2]" value="0.2549902590543216" />
			<parameter name="section.endBase[1][0]" value="-0.6408081100454643" />
			<parameter name="section.endBase[1][1]" value="-0.7043654731982253" />
			<parameter name="section.endBase[1][2]" value="-0.3053428339853421" />
			<parameter name="section.endBase[2][0]" value="9.824251594720002E-5" />
			<parameter name="section.endBase[2][1]" value="-0.3978118510391543" />
			<parameter name="section.endBase[2][2]" value="0.9174670138600132" />
			<parameter name="section.poincareStartVector[0]" value="-0.0499863275749385" />
			<parameter name="section.poincareStartVector[1]" value="0.01000623687979903" />
			<parameter name="section.poincareStartVector[2]" value="1.527871447263583" />
			<parameter name="section.poincareStartVector[3]" value="1.027104556455228" />
			<parameter name="section.poincareStartVector[4]" value="0.006417302061668725" />
			<parameter name="section.poincareStartVector[5]" value="-1.9064725382647754" />
			<parameter name="section.poincareMaxIterRef" value="20" />
			<parameter name="section.poincareMinTime" value="0.0" />
			<parameter name="section.poincareMaxTime" value="20000.0" />
			<parameter name="section.poincareStartBody" value="4" />
			<parameter name="section.poincareEndBody" value="7" />
			<parameter name="section.poincareSense" value="1" />
			<parameter name="section.epoch" value="2459688.585980084" />
			<parameter name="flyByCriterion" value="0.05" />
			<parameter name="aproxTolErr" value="1.0E-6" />
			<parameter name="aproxStepPar" value="5.0E-4" />
			<parameter name="aproxMinStepPar" value="1.0E-11" />
			<parameter name="aproxMaxIter" value="5000" />
			<parameter name="aproxEndBodyDistance" value="0.0050" />
			<parameter name="aproxInitialStartBodyDistance" value="0.01" />
			<parameter name="aproxInitialEndBodyDistance" value="1.0" />
			<parameter name="aproxInitialTime" value="2459503.0" />
		</orbit>
	</result>
	<result operation="Flyby">
		<description>15/11/11 20:30 D:\perso\orbitfinder\24-ESbydv-2021.xml:7
			operation 2 after 204s.</description>
		<orbit>
			<parameter name="aproxMetricPar[0]" value="365.0" />
			<parameter name="aproxMetricPar[1]" value="1.0E-5" />
			<parameter name="aproxMetricPar[2]" value="3.141592653589793" />
			<parameter name="aproxMetricPar[3]" value="6.283185307179586" />
			<parameter name="aproxMetricPar[4]" value="1.0E-5" />
			<parameter name="aproxMetricPar[5]" value="6.283185307179586" />
			<parameter name="section.startBase[0][0]" value="-0.7677010853505211" />
			<parameter name="section.startBase[0][1]" value="0.5878903055324538" />
			<parameter name="section.startBase[0][2]" value="0.2549902590543216" />
			<parameter name="section.startBase[1][0]" value="-0.6408081100454643" />
			<parameter name="section.startBase[1][1]" value="-0.7043654731982253" />
			<parameter name="section.startBase[1][2]" value="-0.3053428339853421" />
			<parameter name="section.startBase[2][0]" value="9.824251594720002E-5" />
			<parameter name="section.startBase[2][1]" value="-0.3978118510391543" />
			<parameter name="section.startBase[2][2]" value="0.9174670138600132" />
			<parameter name="section.endBase[0][0]" value="-0.7677010853505211" />
			<parameter name="section.endBase[0][1]" value="0.5878903055324538" />
			<parameter name="section.endBase[0][2]" value="0.2549902590543216" />
			<parameter name="section.endBase[1][0]" value="-0.6408081100454643" />
			<parameter name="section.endBase[1][1]" value="-0.7043654731982253" />
			<parameter name="section.endBase[1][2]" value="-0.3053428339853421" />
			<parameter name="section.endBase[2][0]" value="9.824251594720002E-5" />
			<parameter name="section.endBase[2][1]" value="-0.3978118510391543" />
			<parameter name="section.endBase[2][2]" value="0.9174670138600132" />
			<parameter name="section.poincareStartVector[0]" value="-0.17229204751236205" />
			<parameter name="section.poincareStartVector[1]" value="0.010007220584384862" />
			<parameter name="section.poincareStartVector[2]" value="1.4891061151702534" />
			<parameter name="section.poincareStartVector[3]" value="1.0027387851846656" />
			<parameter name="section.poincareStartVector[4]" value="0.006417185031332159" />
			<parameter name="section.poincareStartVector[5]" value="-1.8964552173678224" />
			<parameter name="section.poincareMaxIterRef" value="20" />
			<parameter name="section.poincareMinTime" value="0.0" />
			<parameter name="section.poincareMaxTime" value="20000.0" />
			<parameter name="section.poincareStartBody" value="4" />
			<parameter name="section.poincareEndBody" value="7" />
			<parameter name="section.poincareSense" value="1" />
			<parameter name="section.epoch" value="2459691.351855029" />
			<parameter name="flyByCriterion" value="0.05" />
			<parameter name="aproxTolErr" value="1.0E-6" />
			<parameter name="aproxStepPar" value="5.0E-4" />
			<parameter name="aproxMinStepPar" value="1.0E-11" />
			<parameter name="aproxMaxIter" value="5000" />
			<parameter name="aproxEndBodyDistance" value="0.0050" />
			<parameter name="aproxInitialStartBodyDistance" value="0.01" />
			<parameter name="aproxInitialEndBodyDistance" value="0.5" />
			<parameter name="aproxInitialTime" value="2459503.0" />
		</orbit>
	</result>
</orbits>
